[
  {
    "model":"Star, type RK5(iii)",
    "name":"Star, type RK5(iii)",
    "type":"WB_REF",
    "dataQualityMarker":3,
    "dataSource":"https://www.eso.org/sci/facilities/paranal/decommissioned/isaac/tools/lib.html",
    "manufacturer":"A. Pickles (A.J. Pickles, PASP 110,863, 1998)",
    "version":1,
    "wavelength":{
      "value":[
        1150.0,
        1155.0,
        1160.0,
        1165.0,
        1170.0,
        1175.0,
        1180.0,
        1185.0,
        1190.0,
        1195.0,
        1200.0,
        1205.0,
        1210.0,
        1215.0,
        1220.0,
        1225.0,
        1230.0,
        1235.0,
        1240.0,
        1245.0,
        1250.0,
        1255.0,
        1260.0,
        1265.0,
        1270.0,
        1275.0,
        1280.0,
        1285.0,
        1290.0,
        1295.0,
        1300.0,
        1305.0,
        1310.0,
        1315.0,
        1320.0,
        1325.0,
        1330.0,
        1335.0,
        1340.0,
        1345.0,
        1350.0,
        1355.0,
        1360.0,
        1365.0,
        1370.0,
        1375.0,
        1380.0,
        1385.0,
        1390.0,
        1395.0,
        1400.0,
        1405.0,
        1410.0,
        1415.0,
        1420.0,
        1425.0,
        1430.0,
        1435.0,
        1440.0,
        1445.0,
        1450.0,
        1455.0,
        1460.0,
        1465.0,
        1470.0,
        1475.0,
        1480.0,
        1485.0,
        1490.0,
        1495.0,
        1500.0,
        1505.0,
        1510.0,
        1515.0,
        1520.0,
        1525.0,
        1530.0,
        1535.0,
        1540.0,
        1545.0,
        1550.0,
        1555.0,
        1560.0,
        1565.0,
        1570.0,
        1575.0,
        1580.0,
        1585.0,
        1590.0,
        1595.0,
        1600.0,
        1605.0,
        1610.0,
        1615.0,
        1620.0,
        1625.0,
        1630.0,
        1635.0,
        1640.0,
        1645.0,
        1650.0,
        1655.0,
        1660.0,
        1665.0,
        1670.0,
        1675.0,
        1680.0,
        1685.0,
        1690.0,
        1695.0,
        1700.0,
        1705.0,
        1710.0,
        1715.0,
        1720.0,
        1725.0,
        1730.0,
        1735.0,
        1740.0,
        1745.0,
        1750.0,
        1755.0,
        1760.0,
        1765.0,
        1770.0,
        1775.0,
        1780.0,
        1785.0,
        1790.0,
        1795.0,
        1800.0,
        1805.0,
        1810.0,
        1815.0,
        1820.0,
        1825.0,
        1830.0,
        1835.0,
        1840.0,
        1845.0,
        1850.0,
        1855.0,
        1860.0,
        1865.0,
        1870.0,
        1875.0,
        1880.0,
        1885.0,
        1890.0,
        1895.0,
        1900.0,
        1905.0,
        1910.0,
        1915.0,
        1920.0,
        1925.0,
        1930.0,
        1935.0,
        1940.0,
        1945.0,
        1950.0,
        1955.0,
        1960.0,
        1965.0,
        1970.0,
        1975.0,
        1980.0,
        1985.0,
        1990.0,
        1995.0,
        2000.0,
        2005.0,
        2010.0,
        2015.0,
        2020.0,
        2025.0,
        2030.0,
        2035.0,
        2040.0,
        2045.0,
        2050.0,
        2055.0,
        2060.0,
        2065.0,
        2070.0,
        2075.0,
        2080.0,
        2085.0,
        2090.0,
        2095.0,
        2100.0,
        2105.0,
        2110.0,
        2115.0,
        2120.0,
        2125.0,
        2130.0,
        2135.0,
        2140.0,
        2145.0,
        2150.0,
        2155.0,
        2160.0,
        2165.0,
        2170.0,
        2175.0,
        2180.0,
        2185.0,
        2190.0,
        2195.0,
        2200.0,
        2205.0,
        2210.0,
        2215.0,
        2220.0,
        2225.0,
        2230.0,
        2235.0,
        2240.0,
        2245.0,
        2250.0,
        2255.0,
        2260.0,
        2265.0,
        2270.0,
        2275.0,
        2280.0,
        2285.0,
        2290.0,
        2295.0,
        2300.0,
        2305.0,
        2310.0,
        2315.0,
        2320.0,
        2325.0,
        2330.0,
        2335.0,
        2340.0,
        2345.0,
        2350.0,
        2355.0,
        2360.0,
        2365.0,
        2370.0,
        2375.0,
        2380.0,
        2385.0,
        2390.0,
        2395.0,
        2400.0,
        2405.0,
        2410.0,
        2415.0,
        2420.0,
        2425.0,
        2430.0,
        2435.0,
        2440.0,
        2445.0,
        2450.0,
        2455.0,
        2460.0,
        2465.0,
        2470.0,
        2475.0,
        2480.0,
        2485.0,
        2490.0,
        2495.0,
        2500.0,
        2505.0,
        2510.0,
        2515.0,
        2520.0,
        2525.0,
        2530.0,
        2535.0,
        2540.0,
        2545.0,
        2550.0,
        2555.0,
        2560.0,
        2565.0,
        2570.0,
        2575.0,
        2580.0,
        2585.0,
        2590.0,
        2595.0,
        2600.0,
        2605.0,
        2610.0,
        2615.0,
        2620.0,
        2625.0,
        2630.0,
        2635.0,
        2640.0,
        2645.0,
        2650.0,
        2655.0,
        2660.0,
        2665.0,
        2670.0,
        2675.0,
        2680.0,
        2685.0,
        2690.0,
        2695.0,
        2700.0,
        2705.0,
        2710.0,
        2715.0,
        2720.0,
        2725.0,
        2730.0,
        2735.0,
        2740.0,
        2745.0,
        2750.0,
        2755.0,
        2760.0,
        2765.0,
        2770.0,
        2775.0,
        2780.0,
        2785.0,
        2790.0,
        2795.0,
        2800.0,
        2805.0,
        2810.0,
        2815.0,
        2820.0,
        2825.0,
        2830.0,
        2835.0,
        2840.0,
        2845.0,
        2850.0,
        2855.0,
        2860.0,
        2865.0,
        2870.0,
        2875.0,
        2880.0,
        2885.0,
        2890.0,
        2895.0,
        2900.0,
        2905.0,
        2910.0,
        2915.0,
        2920.0,
        2925.0,
        2930.0,
        2935.0,
        2940.0,
        2945.0,
        2950.0,
        2955.0,
        2960.0,
        2965.0,
        2970.0,
        2975.0,
        2980.0,
        2985.0,
        2990.0,
        2995.0,
        3000.0,
        3005.0,
        3010.0,
        3015.0,
        3020.0,
        3025.0,
        3030.0,
        3035.0,
        3040.0,
        3045.0,
        3050.0,
        3055.0,
        3060.0,
        3065.0,
        3070.0,
        3075.0,
        3080.0,
        3085.0,
        3090.0,
        3095.0,
        3100.0,
        3105.0,
        3110.0,
        3115.0,
        3120.0,
        3125.0,
        3130.0,
        3135.0,
        3140.0,
        3145.0,
        3150.0,
        3155.0,
        3160.0,
        3165.0,
        3170.0,
        3175.0,
        3180.0,
        3185.0,
        3190.0,
        3195.0,
        3200.0,
        3205.0,
        3210.0,
        3215.0,
        3220.0,
        3225.0,
        3230.0,
        3235.0,
        3240.0,
        3245.0,
        3250.0,
        3255.0,
        3260.0,
        3265.0,
        3270.0,
        3275.0,
        3280.0,
        3285.0,
        3290.0,
        3295.0,
        3300.0,
        3305.0,
        3310.0,
        3315.0,
        3320.0,
        3325.0,
        3330.0,
        3335.0,
        3340.0,
        3345.0,
        3350.0,
        3355.0,
        3360.0,
        3365.0,
        3370.0,
        3375.0,
        3380.0,
        3385.0,
        3390.0,
        3395.0,
        3400.0,
        3405.0,
        3410.0,
        3415.0,
        3420.0,
        3425.0,
        3430.0,
        3435.0,
        3440.0,
        3445.0,
        3450.0,
        3455.0,
        3460.0,
        3465.0,
        3470.0,
        3475.0,
        3480.0,
        3485.0,
        3490.0,
        3495.0,
        3500.0,
        3505.0,
        3510.0,
        3515.0,
        3520.0,
        3525.0,
        3530.0,
        3535.0,
        3540.0,
        3545.0,
        3550.0,
        3555.0,
        3560.0,
        3565.0,
        3570.0,
        3575.0,
        3580.0,
        3585.0,
        3590.0,
        3595.0,
        3600.0,
        3605.0,
        3610.0,
        3615.0,
        3620.0,
        3625.0,
        3630.0,
        3635.0,
        3640.0,
        3645.0,
        3650.0,
        3655.0,
        3660.0,
        3665.0,
        3670.0,
        3675.0,
        3680.0,
        3685.0,
        3690.0,
        3695.0,
        3700.0,
        3705.0,
        3710.0,
        3715.0,
        3720.0,
        3725.0,
        3730.0,
        3735.0,
        3740.0,
        3745.0,
        3750.0,
        3755.0,
        3760.0,
        3765.0,
        3770.0,
        3775.0,
        3780.0,
        3785.0,
        3790.0,
        3795.0,
        3800.0,
        3805.0,
        3810.0,
        3815.0,
        3820.0,
        3825.0,
        3830.0,
        3835.0,
        3840.0,
        3845.0,
        3850.0,
        3855.0,
        3860.0,
        3865.0,
        3870.0,
        3875.0,
        3880.0,
        3885.0,
        3890.0,
        3895.0,
        3900.0,
        3905.0,
        3910.0,
        3915.0,
        3920.0,
        3925.0,
        3930.0,
        3935.0,
        3940.0,
        3945.0,
        3950.0,
        3955.0,
        3960.0,
        3965.0,
        3970.0,
        3975.0,
        3980.0,
        3985.0,
        3990.0,
        3995.0,
        4000.0,
        4005.0,
        4010.0,
        4015.0,
        4020.0,
        4025.0,
        4030.0,
        4035.0,
        4040.0,
        4045.0,
        4050.0,
        4055.0,
        4060.0,
        4065.0,
        4070.0,
        4075.0,
        4080.0,
        4085.0,
        4090.0,
        4095.0,
        4100.0,
        4105.0,
        4110.0,
        4115.0,
        4120.0,
        4125.0,
        4130.0,
        4135.0,
        4140.0,
        4145.0,
        4150.0,
        4155.0,
        4160.0,
        4165.0,
        4170.0,
        4175.0,
        4180.0,
        4185.0,
        4190.0,
        4195.0,
        4200.0,
        4205.0,
        4210.0,
        4215.0,
        4220.0,
        4225.0,
        4230.0,
        4235.0,
        4240.0,
        4245.0,
        4250.0,
        4255.0,
        4260.0,
        4265.0,
        4270.0,
        4275.0,
        4280.0,
        4285.0,
        4290.0,
        4295.0,
        4300.0,
        4305.0,
        4310.0,
        4315.0,
        4320.0,
        4325.0,
        4330.0,
        4335.0,
        4340.0,
        4345.0,
        4350.0,
        4355.0,
        4360.0,
        4365.0,
        4370.0,
        4375.0,
        4380.0,
        4385.0,
        4390.0,
        4395.0,
        4400.0,
        4405.0,
        4410.0,
        4415.0,
        4420.0,
        4425.0,
        4430.0,
        4435.0,
        4440.0,
        4445.0,
        4450.0,
        4455.0,
        4460.0,
        4465.0,
        4470.0,
        4475.0,
        4480.0,
        4485.0,
        4490.0,
        4495.0,
        4500.0,
        4505.0,
        4510.0,
        4515.0,
        4520.0,
        4525.0,
        4530.0,
        4535.0,
        4540.0,
        4545.0,
        4550.0,
        4555.0,
        4560.0,
        4565.0,
        4570.0,
        4575.0,
        4580.0,
        4585.0,
        4590.0,
        4595.0,
        4600.0,
        4605.0,
        4610.0,
        4615.0,
        4620.0,
        4625.0,
        4630.0,
        4635.0,
        4640.0,
        4645.0,
        4650.0,
        4655.0,
        4660.0,
        4665.0,
        4670.0,
        4675.0,
        4680.0,
        4685.0,
        4690.0,
        4695.0,
        4700.0,
        4705.0,
        4710.0,
        4715.0,
        4720.0,
        4725.0,
        4730.0,
        4735.0,
        4740.0,
        4745.0,
        4750.0,
        4755.0,
        4760.0,
        4765.0,
        4770.0,
        4775.0,
        4780.0,
        4785.0,
        4790.0,
        4795.0,
        4800.0,
        4805.0,
        4810.0,
        4815.0,
        4820.0,
        4825.0,
        4830.0,
        4835.0,
        4840.0,
        4845.0,
        4850.0,
        4855.0,
        4860.0,
        4865.0,
        4870.0,
        4875.0,
        4880.0,
        4885.0,
        4890.0,
        4895.0,
        4900.0,
        4905.0,
        4910.0,
        4915.0,
        4920.0,
        4925.0,
        4930.0,
        4935.0,
        4940.0,
        4945.0,
        4950.0,
        4955.0,
        4960.0,
        4965.0,
        4970.0,
        4975.0,
        4980.0,
        4985.0,
        4990.0,
        4995.0,
        5000.0,
        5005.0,
        5010.0,
        5015.0,
        5020.0,
        5025.0,
        5030.0,
        5035.0,
        5040.0,
        5045.0,
        5050.0,
        5055.0,
        5060.0,
        5065.0,
        5070.0,
        5075.0,
        5080.0,
        5085.0,
        5090.0,
        5095.0,
        5100.0,
        5105.0,
        5110.0,
        5115.0,
        5120.0,
        5125.0,
        5130.0,
        5135.0,
        5140.0,
        5145.0,
        5150.0,
        5155.0,
        5160.0,
        5165.0,
        5170.0,
        5175.0,
        5180.0,
        5185.0,
        5190.0,
        5195.0,
        5200.0,
        5205.0,
        5210.0,
        5215.0,
        5220.0,
        5225.0,
        5230.0,
        5235.0,
        5240.0,
        5245.0,
        5250.0,
        5255.0,
        5260.0,
        5265.0,
        5270.0,
        5275.0,
        5280.0,
        5285.0,
        5290.0,
        5295.0,
        5300.0,
        5305.0,
        5310.0,
        5315.0,
        5320.0,
        5325.0,
        5330.0,
        5335.0,
        5340.0,
        5345.0,
        5350.0,
        5355.0,
        5360.0,
        5365.0,
        5370.0,
        5375.0,
        5380.0,
        5385.0,
        5390.0,
        5395.0,
        5400.0,
        5405.0,
        5410.0,
        5415.0,
        5420.0,
        5425.0,
        5430.0,
        5435.0,
        5440.0,
        5445.0,
        5450.0,
        5455.0,
        5460.0,
        5465.0,
        5470.0,
        5475.0,
        5480.0,
        5485.0,
        5490.0,
        5495.0,
        5500.0,
        5505.0,
        5510.0,
        5515.0,
        5520.0,
        5525.0,
        5530.0,
        5535.0,
        5540.0,
        5545.0,
        5550.0,
        5555.0,
        5560.0,
        5565.0,
        5570.0,
        5575.0,
        5580.0,
        5585.0,
        5590.0,
        5595.0,
        5600.0,
        5605.0,
        5610.0,
        5615.0,
        5620.0,
        5625.0,
        5630.0,
        5635.0,
        5640.0,
        5645.0,
        5650.0,
        5655.0,
        5660.0,
        5665.0,
        5670.0,
        5675.0,
        5680.0,
        5685.0,
        5690.0,
        5695.0,
        5700.0,
        5705.0,
        5710.0,
        5715.0,
        5720.0,
        5725.0,
        5730.0,
        5735.0,
        5740.0,
        5745.0,
        5750.0,
        5755.0,
        5760.0,
        5765.0,
        5770.0,
        5775.0,
        5780.0,
        5785.0,
        5790.0,
        5795.0,
        5800.0,
        5805.0,
        5810.0,
        5815.0,
        5820.0,
        5825.0,
        5830.0,
        5835.0,
        5840.0,
        5845.0,
        5850.0,
        5855.0,
        5860.0,
        5865.0,
        5870.0,
        5875.0,
        5880.0,
        5885.0,
        5890.0,
        5895.0,
        5900.0,
        5905.0,
        5910.0,
        5915.0,
        5920.0,
        5925.0,
        5930.0,
        5935.0,
        5940.0,
        5945.0,
        5950.0,
        5955.0,
        5960.0,
        5965.0,
        5970.0,
        5975.0,
        5980.0,
        5985.0,
        5990.0,
        5995.0,
        6000.0,
        6005.0,
        6010.0,
        6015.0,
        6020.0,
        6025.0,
        6030.0,
        6035.0,
        6040.0,
        6045.0,
        6050.0,
        6055.0,
        6060.0,
        6065.0,
        6070.0,
        6075.0,
        6080.0,
        6085.0,
        6090.0,
        6095.0,
        6100.0,
        6105.0,
        6110.0,
        6115.0,
        6120.0,
        6125.0,
        6130.0,
        6135.0,
        6140.0,
        6145.0,
        6150.0,
        6155.0,
        6160.0,
        6165.0,
        6170.0,
        6175.0,
        6180.0,
        6185.0,
        6190.0,
        6195.0,
        6200.0,
        6205.0,
        6210.0,
        6215.0,
        6220.0,
        6225.0,
        6230.0,
        6235.0,
        6240.0,
        6245.0,
        6250.0,
        6255.0,
        6260.0,
        6265.0,
        6270.0,
        6275.0,
        6280.0,
        6285.0,
        6290.0,
        6295.0,
        6300.0,
        6305.0,
        6310.0,
        6315.0,
        6320.0,
        6325.0,
        6330.0,
        6335.0,
        6340.0,
        6345.0,
        6350.0,
        6355.0,
        6360.0,
        6365.0,
        6370.0,
        6375.0,
        6380.0,
        6385.0,
        6390.0,
        6395.0,
        6400.0,
        6405.0,
        6410.0,
        6415.0,
        6420.0,
        6425.0,
        6430.0,
        6435.0,
        6440.0,
        6445.0,
        6450.0,
        6455.0,
        6460.0,
        6465.0,
        6470.0,
        6475.0,
        6480.0,
        6485.0,
        6490.0,
        6495.0,
        6500.0,
        6505.0,
        6510.0,
        6515.0,
        6520.0,
        6525.0,
        6530.0,
        6535.0,
        6540.0,
        6545.0,
        6550.0,
        6555.0,
        6560.0,
        6565.0,
        6570.0,
        6575.0,
        6580.0,
        6585.0,
        6590.0,
        6595.0,
        6600.0,
        6605.0,
        6610.0,
        6615.0,
        6620.0,
        6625.0,
        6630.0,
        6635.0,
        6640.0,
        6645.0,
        6650.0,
        6655.0,
        6660.0,
        6665.0,
        6670.0,
        6675.0,
        6680.0,
        6685.0,
        6690.0,
        6695.0,
        6700.0,
        6705.0,
        6710.0,
        6715.0,
        6720.0,
        6725.0,
        6730.0,
        6735.0,
        6740.0,
        6745.0,
        6750.0,
        6755.0,
        6760.0,
        6765.0,
        6770.0,
        6775.0,
        6780.0,
        6785.0,
        6790.0,
        6795.0,
        6800.0,
        6805.0,
        6810.0,
        6815.0,
        6820.0,
        6825.0,
        6830.0,
        6835.0,
        6840.0,
        6845.0,
        6850.0,
        6855.0,
        6860.0,
        6865.0,
        6870.0,
        6875.0,
        6880.0,
        6885.0,
        6890.0,
        6895.0,
        6900.0,
        6905.0,
        6910.0,
        6915.0,
        6920.0,
        6925.0,
        6930.0,
        6935.0,
        6940.0,
        6945.0,
        6950.0,
        6955.0,
        6960.0,
        6965.0,
        6970.0,
        6975.0,
        6980.0,
        6985.0,
        6990.0,
        6995.0,
        7000.0,
        7005.0,
        7010.0,
        7015.0,
        7020.0,
        7025.0,
        7030.0,
        7035.0,
        7040.0,
        7045.0,
        7050.0,
        7055.0,
        7060.0,
        7065.0,
        7070.0,
        7075.0,
        7080.0,
        7085.0,
        7090.0,
        7095.0,
        7100.0,
        7105.0,
        7110.0,
        7115.0,
        7120.0,
        7125.0,
        7130.0,
        7135.0,
        7140.0,
        7145.0,
        7150.0,
        7155.0,
        7160.0,
        7165.0,
        7170.0,
        7175.0,
        7180.0,
        7185.0,
        7190.0,
        7195.0,
        7200.0,
        7205.0,
        7210.0,
        7215.0,
        7220.0,
        7225.0,
        7230.0,
        7235.0,
        7240.0,
        7245.0,
        7250.0,
        7255.0,
        7260.0,
        7265.0,
        7270.0,
        7275.0,
        7280.0,
        7285.0,
        7290.0,
        7295.0,
        7300.0,
        7305.0,
        7310.0,
        7315.0,
        7320.0,
        7325.0,
        7330.0,
        7335.0,
        7340.0,
        7345.0,
        7350.0,
        7355.0,
        7360.0,
        7365.0,
        7370.0,
        7375.0,
        7380.0,
        7385.0,
        7390.0,
        7395.0,
        7400.0,
        7405.0,
        7410.0,
        7415.0,
        7420.0,
        7425.0,
        7430.0,
        7435.0,
        7440.0,
        7445.0,
        7450.0,
        7455.0,
        7460.0,
        7465.0,
        7470.0,
        7475.0,
        7480.0,
        7485.0,
        7490.0,
        7495.0,
        7500.0,
        7505.0,
        7510.0,
        7515.0,
        7520.0,
        7525.0,
        7530.0,
        7535.0,
        7540.0,
        7545.0,
        7550.0,
        7555.0,
        7560.0,
        7565.0,
        7570.0,
        7575.0,
        7580.0,
        7585.0,
        7590.0,
        7595.0,
        7600.0,
        7605.0,
        7610.0,
        7615.0,
        7620.0,
        7625.0,
        7630.0,
        7635.0,
        7640.0,
        7645.0,
        7650.0,
        7655.0,
        7660.0,
        7665.0,
        7670.0,
        7675.0,
        7680.0,
        7685.0,
        7690.0,
        7695.0,
        7700.0,
        7705.0,
        7710.0,
        7715.0,
        7720.0,
        7725.0,
        7730.0,
        7735.0,
        7740.0,
        7745.0,
        7750.0,
        7755.0,
        7760.0,
        7765.0,
        7770.0,
        7775.0,
        7780.0,
        7785.0,
        7790.0,
        7795.0,
        7800.0,
        7805.0,
        7810.0,
        7815.0,
        7820.0,
        7825.0,
        7830.0,
        7835.0,
        7840.0,
        7845.0,
        7850.0,
        7855.0,
        7860.0,
        7865.0,
        7870.0,
        7875.0,
        7880.0,
        7885.0,
        7890.0,
        7895.0,
        7900.0,
        7905.0,
        7910.0,
        7915.0,
        7920.0,
        7925.0,
        7930.0,
        7935.0,
        7940.0,
        7945.0,
        7950.0,
        7955.0,
        7960.0,
        7965.0,
        7970.0,
        7975.0,
        7980.0,
        7985.0,
        7990.0,
        7995.0,
        8000.0,
        8005.0,
        8010.0,
        8015.0,
        8020.0,
        8025.0,
        8030.0,
        8035.0,
        8040.0,
        8045.0,
        8050.0,
        8055.0,
        8060.0,
        8065.0,
        8070.0,
        8075.0,
        8080.0,
        8085.0,
        8090.0,
        8095.0,
        8100.0,
        8105.0,
        8110.0,
        8115.0,
        8120.0,
        8125.0,
        8130.0,
        8135.0,
        8140.0,
        8145.0,
        8150.0,
        8155.0,
        8160.0,
        8165.0,
        8170.0,
        8175.0,
        8180.0,
        8185.0,
        8190.0,
        8195.0,
        8200.0,
        8205.0,
        8210.0,
        8215.0,
        8220.0,
        8225.0,
        8230.0,
        8235.0,
        8240.0,
        8245.0,
        8250.0,
        8255.0,
        8260.0,
        8265.0,
        8270.0,
        8275.0,
        8280.0,
        8285.0,
        8290.0,
        8295.0,
        8300.0,
        8305.0,
        8310.0,
        8315.0,
        8320.0,
        8325.0,
        8330.0,
        8335.0,
        8340.0,
        8345.0,
        8350.0,
        8355.0,
        8360.0,
        8365.0,
        8370.0,
        8375.0,
        8380.0,
        8385.0,
        8390.0,
        8395.0,
        8400.0,
        8405.0,
        8410.0,
        8415.0,
        8420.0,
        8425.0,
        8430.0,
        8435.0,
        8440.0,
        8445.0,
        8450.0,
        8455.0,
        8460.0,
        8465.0,
        8470.0,
        8475.0,
        8480.0,
        8485.0,
        8490.0,
        8495.0,
        8500.0,
        8505.0,
        8510.0,
        8515.0,
        8520.0,
        8525.0,
        8530.0,
        8535.0,
        8540.0,
        8545.0,
        8550.0,
        8555.0,
        8560.0,
        8565.0,
        8570.0,
        8575.0,
        8580.0,
        8585.0,
        8590.0,
        8595.0,
        8600.0,
        8605.0,
        8610.0,
        8615.0,
        8620.0,
        8625.0,
        8630.0,
        8635.0,
        8640.0,
        8645.0,
        8650.0,
        8655.0,
        8660.0,
        8665.0,
        8670.0,
        8675.0,
        8680.0,
        8685.0,
        8690.0,
        8695.0,
        8700.0,
        8705.0,
        8710.0,
        8715.0,
        8720.0,
        8725.0,
        8730.0,
        8735.0,
        8740.0,
        8745.0,
        8750.0,
        8755.0,
        8760.0,
        8765.0,
        8770.0,
        8775.0,
        8780.0,
        8785.0,
        8790.0,
        8795.0,
        8800.0,
        8805.0,
        8810.0,
        8815.0,
        8820.0,
        8825.0,
        8830.0,
        8835.0,
        8840.0,
        8845.0,
        8850.0,
        8855.0,
        8860.0,
        8865.0,
        8870.0,
        8875.0,
        8880.0,
        8885.0,
        8890.0,
        8895.0,
        8900.0,
        8905.0,
        8910.0,
        8915.0,
        8920.0,
        8925.0,
        8930.0,
        8935.0,
        8940.0,
        8945.0,
        8950.0,
        8955.0,
        8960.0,
        8965.0,
        8970.0,
        8975.0,
        8980.0,
        8985.0,
        8990.0,
        8995.0,
        9000.0,
        9005.0,
        9010.0,
        9015.0,
        9020.0,
        9025.0,
        9030.0,
        9035.0,
        9040.0,
        9045.0,
        9050.0,
        9055.0,
        9060.0,
        9065.0,
        9070.0,
        9075.0,
        9080.0,
        9085.0,
        9090.0,
        9095.0,
        9100.0,
        9105.0,
        9110.0,
        9115.0,
        9120.0,
        9125.0,
        9130.0,
        9135.0,
        9140.0,
        9145.0,
        9150.0,
        9155.0,
        9160.0,
        9165.0,
        9170.0,
        9175.0,
        9180.0,
        9185.0,
        9190.0,
        9195.0,
        9200.0,
        9205.0,
        9210.0,
        9215.0,
        9220.0,
        9225.0,
        9230.0,
        9235.0,
        9240.0,
        9245.0,
        9250.0,
        9255.0,
        9260.0,
        9265.0,
        9270.0,
        9275.0,
        9280.0,
        9285.0,
        9290.0,
        9295.0,
        9300.0,
        9305.0,
        9310.0,
        9315.0,
        9320.0,
        9325.0,
        9330.0,
        9335.0,
        9340.0,
        9345.0,
        9350.0,
        9355.0,
        9360.0,
        9365.0,
        9370.0,
        9375.0,
        9380.0,
        9385.0,
        9390.0,
        9395.0,
        9400.0,
        9405.0,
        9410.0,
        9415.0,
        9420.0,
        9425.0,
        9430.0,
        9435.0,
        9440.0,
        9445.0,
        9450.0,
        9455.0,
        9460.0,
        9465.0,
        9470.0,
        9475.0,
        9480.0,
        9485.0,
        9490.0,
        9495.0,
        9500.0,
        9505.0,
        9510.0,
        9515.0,
        9520.0,
        9525.0,
        9530.0,
        9535.0,
        9540.0,
        9545.0,
        9550.0,
        9555.0,
        9560.0,
        9565.0,
        9570.0,
        9575.0,
        9580.0,
        9585.0,
        9590.0,
        9595.0,
        9600.0,
        9605.0,
        9610.0,
        9615.0,
        9620.0,
        9625.0,
        9630.0,
        9635.0,
        9640.0,
        9645.0,
        9650.0,
        9655.0,
        9660.0,
        9665.0,
        9670.0,
        9675.0,
        9680.0,
        9685.0,
        9690.0,
        9695.0,
        9700.0,
        9705.0,
        9710.0,
        9715.0,
        9720.0,
        9725.0,
        9730.0,
        9735.0,
        9740.0,
        9745.0,
        9750.0,
        9755.0,
        9760.0,
        9765.0,
        9770.0,
        9775.0,
        9780.0,
        9785.0,
        9790.0,
        9795.0,
        9800.0,
        9805.0,
        9810.0,
        9815.0,
        9820.0,
        9825.0,
        9830.0,
        9835.0,
        9840.0,
        9845.0,
        9850.0,
        9855.0,
        9860.0,
        9865.0,
        9870.0,
        9875.0,
        9880.0,
        9885.0,
        9890.0,
        9895.0,
        9900.0,
        9905.0,
        9910.0,
        9915.0,
        9920.0,
        9925.0,
        9930.0,
        9935.0,
        9940.0,
        9945.0,
        9950.0,
        9955.0,
        9960.0,
        9965.0,
        9970.0,
        9975.0,
        9980.0,
        9985.0,
        9990.0,
        9995.0,
        10000.0,
        10005.0,
        10010.0,
        10015.0,
        10020.0,
        10025.0,
        10030.0,
        10035.0,
        10040.0,
        10045.0,
        10050.0,
        10055.0,
        10060.0,
        10065.0,
        10070.0,
        10075.0,
        10080.0,
        10085.0,
        10090.0,
        10095.0,
        10100.0,
        10105.0,
        10110.0,
        10115.0,
        10120.0,
        10125.0,
        10130.0,
        10135.0,
        10140.0,
        10145.0,
        10150.0,
        10155.0,
        10160.0,
        10165.0,
        10170.0,
        10175.0,
        10180.0,
        10185.0,
        10190.0,
        10195.0,
        10200.0,
        10205.0,
        10210.0,
        10215.0,
        10220.0,
        10225.0,
        10230.0,
        10235.0,
        10240.0,
        10245.0,
        10250.0,
        10255.0,
        10260.0,
        10265.0,
        10270.0,
        10275.0,
        10280.0,
        10285.0,
        10290.0,
        10295.0,
        10300.0,
        10305.0,
        10310.0,
        10315.0,
        10320.0,
        10325.0,
        10330.0,
        10335.0,
        10340.0,
        10345.0,
        10350.0,
        10355.0,
        10360.0,
        10365.0,
        10370.0,
        10375.0,
        10380.0,
        10385.0,
        10390.0,
        10395.0,
        10400.0,
        10405.0,
        10410.0,
        10415.0,
        10420.0,
        10425.0,
        10430.0,
        10435.0,
        10440.0,
        10445.0,
        10450.0,
        10455.0,
        10460.0,
        10465.0,
        10470.0,
        10475.0,
        10480.0,
        10485.0,
        10490.0,
        10495.0,
        10500.0
      ],
      "units":"angstrom"
    },
    "values":{
      "value":[
        0.0,
        0.0,
        0.0,
        0.0,
        0.0,
        0.0,
        0.0,
        0.0,
        0.0,
        0.0,
        0.0,
        0.0,
        0.0,
        0.0,
        0.0,
        0.0,
        0.0,
        0.0,
        0.0,
        0.0,
        0.0,
        0.0,
        0.0,
        0.0,
        0.0,
        0.0,
        0.0,
        0.0,
        0.0,
        0.0,
        0.0,
        0.0,
        0.0,
        0.0,
        0.0,
        0.0,
        0.0,
        0.0,
        0.0,
        0.0,
        0.0,
        0.0,
        0.0,
        0.0,
        0.0,
        0.0,
        0.0,
        0.0,
        0.0,
        0.0,
        0.0,
        0.0,
        0.0,
        0.0,
        0.0,
        0.0,
        0.0,
        0.0,
        0.0,
        0.0,
        0.0,
        0.0,
        0.0,
        0.0,
        0.0,
        0.0,
        0.0,
        0.0,
        0.0,
        0.0,
        0.0,
        0.0,
        0.0,
        0.0,
        0.0,
        0.0,
        0.0,
        0.0,
        0.0,
        0.0,
        0.0,
        0.0,
        0.0,
        0.0,
        0.0,
        0.0,
        0.0,
        0.0,
        0.0,
        0.0,
        0.0,
        0.0,
        0.0,
        0.0,
        0.0,
        0.0,
        0.0,
        0.0,
        0.0,
        0.0,
        0.0,
        0.0,
        0.0,
        0.0,
        0.0,
        0.0,
        0.0,
        0.0,
        0.0,
        0.0,
        0.0,
        0.0,
        0.0,
        0.0,
        0.0,
        0.0,
        0.0,
        0.0,
        0.0,
        0.0,
        0.0,
        0.0,
        0.0,
        0.0,
        0.0,
        0.0,
        0.0,
        0.0,
        0.0,
        0.0,
        0.0,
        0.0,
        0.0,
        0.0,
        0.0,
        0.0,
        0.0,
        0.0,
        0.0,
        0.0,
        0.0,
        0.0,
        0.0,
        0.0,
        0.0,
        0.0,
        0.0,
        0.0,
        0.0,
        0.0,
        0.0,
        0.0,
        0.0,
        0.0,
        0.0,
        0.0,
        0.0,
        0.0,
        0.0,
        0.0,
        0.0,
        0.0,
        0.0,
        0.0,
        0.0,
        0.0,
        0.0,
        0.0,
        0.0,
        0.0,
        0.0,
        0.0,
        0.0,
        0.0,
        0.0,
        0.0,
        0.0,
        0.0,
        0.0,
        0.0,
        0.0,
        0.0,
        0.0,
        0.0,
        0.0,
        0.0,
        0.0,
        0.0,
        0.0,
        0.0,
        0.0,
        0.0,
        0.0,
        0.0,
        0.0,
        0.0,
        0.0,
        0.0,
        0.0,
        0.0,
        0.0,
        0.0,
        0.0,
        0.0,
        0.0,
        0.0,
        0.0,
        0.0,
        0.0,
        0.0,
        0.0,
        0.0,
        0.0,
        0.0,
        0.0,
        0.0,
        0.0,
        0.0,
        0.0,
        0.0,
        0.0,
        0.0,
        0.0,
        0.0,
        0.0,
        0.0,
        0.0,
        0.0,
        0.0,
        0.0,
        0.0,
        0.0,
        0.0,
        0.0,
        0.0,
        0.0,
        0.0,
        0.0,
        0.0,
        0.0,
        0.0,
        0.0,
        0.0,
        0.0,
        0.0,
        0.0,
        0.0,
        0.0,
        0.0,
        0.0,
        0.0,
        0.0,
        0.0,
        0.0,
        0.0,
        0.0,
        0.0,
        0.0,
        0.0,
        0.0,
        0.0,
        0.0,
        0.0,
        0.0,
        0.0,
        0.0,
        0.0,
        0.0,
        0.0,
        0.0,
        0.0,
        0.0,
        1e-06,
        2e-06,
        2e-06,
        2e-06,
        3e-06,
        2e-06,
        2e-06,
        1e-06,
        0.0,
        0.0,
        0.0,
        0.0,
        0.0,
        0.0,
        0.0,
        0.0,
        0.0,
        0.0,
        0.0,
        6e-06,
        1.4e-05,
        2.2e-05,
        2.8e-05,
        3.4e-05,
        3.6e-05,
        3.5e-05,
        2.9e-05,
        1.8e-05,
        0.0,
        0.0,
        0.0,
        0.0,
        0.0,
        0.0,
        0.0,
        0.0,
        0.0,
        0.0,
        0.0,
        9.2e-05,
        0.000211,
        0.000354,
        0.000521,
        0.00071,
        0.00092,
        0.00115,
        0.001398,
        0.001664,
        0.001945,
        0.002239,
        0.002539,
        0.002832,
        0.00311,
        0.003363,
        0.00358,
        0.003751,
        0.003866,
        0.003916,
        0.00389,
        0.003782,
        0.003607,
        0.003382,
        0.003126,
        0.002857,
        0.002592,
        0.00235,
        0.00215,
        0.002009,
        0.001945,
        0.001971,
        0.002077,
        0.002247,
        0.002464,
        0.002714,
        0.00298,
        0.003247,
        0.003498,
        0.003717,
        0.00389,
        0.004004,
        0.004072,
        0.004109,
        0.004131,
        0.004155,
        0.004196,
        0.004272,
        0.004397,
        0.004588,
        0.004862,
        0.005229,
        0.005674,
        0.006178,
        0.006723,
        0.007287,
        0.007852,
        0.008397,
        0.008905,
        0.009353,
        0.009724,
        0.010005,
        0.010209,
        0.010359,
        0.010475,
        0.010579,
        0.010693,
        0.010838,
        0.011034,
        0.011304,
        0.011669,
        0.012143,
        0.012708,
        0.013339,
        0.014011,
        0.014699,
        0.015378,
        0.016023,
        0.016609,
        0.017111,
        0.017504,
        0.017771,
        0.017931,
        0.018009,
        0.018031,
        0.018025,
        0.018015,
        0.01803,
        0.018094,
        0.018234,
        0.018476,
        0.018839,
        0.019302,
        0.019839,
        0.020422,
        0.021023,
        0.021615,
        0.02217,
        0.022661,
        0.02306,
        0.025398,
        0.02623,
        0.024952,
        0.022578,
        0.020648,
        0.020298,
        0.020529,
        0.020186,
        0.01963,
        0.019531,
        0.020285,
        0.021993,
        0.023841,
        0.024878,
        0.024545,
        0.023006,
        0.022957,
        0.026488,
        0.03074,
        0.032535,
        0.032353,
        0.031547,
        0.031294,
        0.032283,
        0.033419,
        0.033585,
        0.03334,
        0.033482,
        0.034075,
        0.034804,
        0.03457,
        0.032685,
        0.030912,
        0.030978,
        0.032018,
        0.032874,
        0.033791,
        0.035185,
        0.036744,
        0.037997,
        0.038544,
        0.038304,
        0.038371,
        0.039702,
        0.041528,
        0.042662,
        0.041974,
        0.03901,
        0.035964,
        0.03511,
        0.036379,
        0.038816,
        0.040271,
        0.039266,
        0.038221,
        0.039471,
        0.041125,
        0.041116,
        0.040891,
        0.042163,
        0.044192,
        0.04561,
        0.035061,
        0.03552,
        0.036309,
        0.040557,
        0.048629,
        0.055905,
        0.058482,
        0.056355,
        0.05369,
        0.05173,
        0.047798,
        0.042398,
        0.036482,
        0.03059,
        0.027619,
        0.02886,
        0.03422,
        0.041126,
        0.044211,
        0.042876,
        0.043644,
        0.048779,
        0.054536,
        0.059187,
        0.061145,
        0.063,
        0.064223,
        0.062941,
        0.0662,
        0.075527,
        0.082316,
        0.082196,
        0.078825,
        0.074613,
        0.070706,
        0.070891,
        0.076247,
        0.081138,
        0.079697,
        0.072867,
        0.067858,
        0.064134,
        0.057765,
        0.052612,
        0.047624,
        0.043355,
        0.042339,
        0.043117,
        0.04671,
        0.051934,
        0.057227,
        0.0648,
        0.073839,
        0.080617,
        0.08159,
        0.074965,
        0.067847,
        0.067609,
        0.070496,
        0.053101,
        0.068295,
        0.061883,
        0.053408,
        0.045281,
        0.037275,
        0.040554,
        0.05382,
        0.055888,
        0.049761,
        0.045904,
        0.045904,
        0.048207,
        0.053346,
        0.056096,
        0.050696,
        0.053835,
        0.065289,
        0.069798,
        0.070572,
        0.076915,
        0.079782,
        0.081283,
        0.071128,
        0.051602,
        0.04365,
        0.034765,
        0.041783,
        0.061053,
        0.074347,
        0.07204,
        0.062831,
        0.055946,
        0.05334,
        0.071098,
        0.09614,
        0.115878,
        0.136013,
        0.140748,
        0.147981,
        0.161638,
        0.177131,
        0.185652,
        0.181182,
        0.172273,
        0.160803,
        0.156947,
        0.160191,
        0.1644,
        0.170063,
        0.17341,
        0.173544,
        0.165184,
        0.163843,
        0.180529,
        0.200151,
        0.219319,
        0.225424,
        0.212014,
        0.19795,
        0.197666,
        0.200285,
        0.199462,
        0.197529,
        0.192029,
        0.178899,
        0.171105,
        0.178147,
        0.17989,
        0.183029,
        0.194364,
        0.202027,
        0.197668,
        0.193128,
        0.19158,
        0.199649,
        0.209993,
        0.212917,
        0.205137,
        0.197487,
        0.204448,
        0.213966,
        0.211588,
        0.187688,
        0.157808,
        0.165475,
        0.209688,
        0.252187,
        0.264931,
        0.251609,
        0.241094,
        0.247738,
        0.25684,
        0.252009,
        0.243356,
        0.246593,
        0.248798,
        0.238471,
        0.237112,
        0.233185,
        0.238608,
        0.272746,
        0.321093,
        0.347832,
        0.357311,
        0.370656,
        0.384028,
        0.39036,
        0.396007,
        0.403901,
        0.412809,
        0.428766,
        0.430639,
        0.412583,
        0.382168,
        0.345609,
        0.332561,
        0.354543,
        0.380157,
        0.382743,
        0.370484,
        0.37234,
        0.400459,
        0.419983,
        0.425138,
        0.428673,
        0.440961,
        0.461634,
        0.478241,
        0.475112,
        0.451441,
        0.437937,
        0.45734,
        0.498061,
        0.533844,
        0.549903,
        0.550218,
        0.541503,
        0.541743,
        0.563936,
        0.599931,
        0.601762,
        0.583486,
        0.558401,
        0.514642,
        0.490556,
        0.506927,
        0.536147,
        0.558309,
        0.574755,
        0.605492,
        0.63881,
        0.648537,
        0.648262,
        0.638915,
        0.628075,
        0.625053,
        0.619153,
        0.611912,
        0.615375,
        0.644943,
        0.695976,
        0.733673,
        0.737419,
        0.712125,
        0.682909,
        0.644795,
        0.60987,
        0.596105,
        0.61095,
        0.642,
        0.661291,
        0.642059,
        0.606716,
        0.615574,
        0.634217,
        0.633002,
        0.639463,
        0.648125,
        0.646039,
        0.645618,
        0.644267,
        0.661342,
        0.685456,
        0.67852,
        0.659969,
        0.67399,
        0.697533,
        0.704977,
        0.707522,
        0.689097,
        0.653475,
        0.619934,
        0.621882,
        0.636976,
        0.633568,
        0.63425,
        0.658178,
        0.695696,
        0.706475,
        0.699288,
        0.693412,
        0.706516,
        0.715451,
        0.70628,
        0.693293,
        0.698666,
        0.690926,
        0.69128,
        0.683189,
        0.666691,
        0.64788,
        0.652531,
        0.657035,
        0.668605,
        0.682346,
        0.666019,
        0.672855,
        0.730613,
        0.755463,
        0.754748,
        0.744816,
        0.745139,
        0.715071,
        0.744354,
        0.789109,
        0.770698,
        0.759345,
        0.801257,
        0.813338,
        0.753893,
        0.693891,
        0.689775,
        0.707808,
        0.719545,
        0.683344,
        0.671393,
        0.691579,
        0.691862,
        0.658519,
        0.633085,
        0.628569,
        0.617847,
        0.63273,
        0.663344,
        0.689613,
        0.692057,
        0.67228,
        0.693302,
        0.708226,
        0.72949,
        0.745553,
        0.718337,
        0.694539,
        0.686453,
        0.655409,
        0.664608,
        0.696413,
        0.698311,
        0.673214,
        0.665482,
        0.663995,
        0.685397,
        0.686047,
        0.647797,
        0.656323,
        0.685061,
        0.682654,
        0.664911,
        0.644703,
        0.667366,
        0.67756,
        0.58685,
        0.504065,
        0.50773,
        0.530249,
        0.570029,
        0.62422,
        0.652532,
        0.651724,
        0.597734,
        0.613447,
        0.708432,
        0.756318,
        0.750704,
        0.76468,
        0.811238,
        0.834799,
        0.808868,
        0.777994,
        0.782891,
        0.771982,
        0.710431,
        0.694933,
        0.786487,
        0.870203,
        0.905549,
        0.919339,
        0.898394,
        0.887261,
        0.945097,
        0.979925,
        0.964456,
        0.924157,
        0.859291,
        0.849436,
        0.89465,
        0.902828,
        0.908412,
        0.951867,
        1.02274,
        1.036484,
        0.991585,
        0.947124,
        0.979936,
        1.008178,
        0.986128,
        0.940664,
        0.905254,
        0.886552,
        0.87805,
        0.909554,
        0.993555,
        1.025413,
        1.015778,
        0.966614,
        0.946572,
        0.99909,
        0.978289,
        0.932339,
        0.893308,
        0.914134,
        0.928175,
        0.927847,
        0.90695,
        0.907977,
        0.92773,
        0.945843,
        0.954289,
        0.949126,
        0.942286,
        0.926515,
        0.931685,
        0.974182,
        0.997474,
        1.00377,
        1.011653,
        1.029956,
        1.042696,
        1.057599,
        1.04314,
        1.026846,
        1.018593,
        1.024483,
        1.038132,
        1.032968,
        0.990506,
        0.959712,
        0.966745,
        0.964968,
        0.993732,
        1.02307,
        1.00677,
        0.987724,
        0.973436,
        0.988005,
        0.99411,
        0.988603,
        0.996018,
        1.017764,
        1.021166,
        0.999608,
        1.001247,
        1.020011,
        1.052579,
        1.067122,
        1.066847,
        1.081906,
        1.077843,
        1.03876,
        1.010941,
        0.997776,
        1.04228,
        1.086311,
        1.100912,
        1.094322,
        1.100039,
        1.098144,
        1.098678,
        1.094542,
        1.105356,
        1.110153,
        1.114965,
        1.126181,
        1.109624,
        1.06766,
        1.041736,
        1.070687,
        1.119212,
        1.155402,
        1.148048,
        1.163506,
        1.17618,
        1.198781,
        1.200714,
        1.197104,
        1.184497,
        1.188638,
        1.203171,
        1.16976,
        1.133026,
        1.122716,
        1.115434,
        1.121345,
        1.116005,
        1.070198,
        0.988327,
        0.844833,
        0.821229,
        0.913581,
        1.010466,
        1.061371,
        1.080119,
        1.096371,
        1.104542,
        1.112885,
        1.117549,
        1.114612,
        1.128435,
        1.123527,
        1.116603,
        1.130581,
        1.148455,
        1.163509,
        1.153869,
        1.13208,
        1.123921,
        1.143559,
        1.156428,
        1.147388,
        1.140335,
        1.135337,
        1.130699,
        1.136664,
        1.168657,
        1.201575,
        1.230683,
        1.240644,
        1.255028,
        1.253641,
        1.229759,
        1.218552,
        1.222537,
        1.257045,
        1.258971,
        1.229529,
        1.208028,
        1.197544,
        1.199435,
        1.197283,
        1.195581,
        1.215552,
        1.222834,
        1.198092,
        1.184962,
        1.201481,
        1.166334,
        1.185216,
        1.221635,
        1.207874,
        1.176445,
        1.107388,
        1.073612,
        1.087448,
        1.11297,
        1.131216,
        1.112558,
        1.072526,
        1.081604,
        1.109637,
        1.123017,
        1.098871,
        1.044399,
        1.02254,
        1.016357,
        0.999833,
        1.022619,
        1.01211,
        1.012022,
        1.033266,
        1.010854,
        1.01159,
        1.059348,
        1.076164,
        1.087432,
        1.089826,
        1.124673,
        1.14155,
        1.115611,
        1.120224,
        1.139535,
        1.149283,
        1.142929,
        1.152028,
        1.177912,
        1.197623,
        1.194976,
        1.192565,
        1.180843,
        1.189737,
        1.16204,
        1.121283,
        1.147483,
        1.21009,
        1.233731,
        1.237269,
        1.244117,
        1.23575,
        1.230791,
        1.228464,
        1.234579,
        1.232129,
        1.227934,
        1.230007,
        1.254211,
        1.248994,
        1.254521,
        1.267433,
        1.265925,
        1.232283,
        1.258302,
        1.274045,
        1.274529,
        1.280325,
        1.271556,
        1.249216,
        1.229434,
        1.196595,
        1.13405,
        1.151922,
        1.208191,
        1.239605,
        1.262318,
        1.272301,
        1.28173,
        1.275746,
        1.284577,
        1.285475,
        1.265488,
        1.242534,
        1.216424,
        1.175898,
        1.180557,
        1.216758,
        1.229688,
        1.256671,
        1.279258,
        1.281166,
        1.261585,
        1.269343,
        1.266756,
        1.26653,
        1.293049,
        1.291833,
        1.273093,
        1.266157,
        1.267698,
        1.275768,
        1.275519,
        1.267864,
        1.25982,
        1.248534,
        1.239937,
        1.259398,
        1.25457,
        1.234832,
        1.246432,
        1.247962,
        1.247799,
        1.255442,
        1.258267,
        1.242871,
        1.21053,
        1.202594,
        1.214988,
        1.221843,
        1.221086,
        1.208295,
        1.201258,
        1.193144,
        1.210772,
        1.238822,
        1.241486,
        1.245871,
        1.266128,
        1.260373,
        1.226013,
        1.233467,
        1.240815,
        1.261016,
        1.268607,
        1.266327,
        1.265003,
        1.272957,
        1.279428,
        1.27559,
        1.284452,
        1.275541,
        1.281772,
        1.278981,
        1.267591,
        1.263393,
        1.276179,
        1.269659,
        1.263472,
        1.272811,
        1.286593,
        1.312949,
        1.324751,
        1.330472,
        1.330118,
        1.317645,
        1.313317,
        1.320294,
        1.312725,
        1.317276,
        1.316689,
        1.314803,
        1.296901,
        1.298697,
        1.298995,
        1.318968,
        1.324569,
        1.323115,
        1.296643,
        1.277736,
        1.307109,
        1.307853,
        1.306969,
        1.298859,
        1.301168,
        1.310221,
        1.288032,
        1.297902,
        1.281283,
        1.298535,
        1.314803,
        1.338309,
        1.357935,
        1.344582,
        1.283907,
        1.250909,
        1.219134,
        1.239966,
        1.300553,
        1.320609,
        1.267928,
        1.209581,
        1.189849,
        1.174773,
        1.173809,
        1.182825,
        1.21745,
        1.232574,
        1.183406,
        1.120761,
        1.12712,
        1.139552,
        1.158471,
        1.168459,
        1.192807,
        1.193654,
        1.194391,
        1.22071,
        1.242561,
        1.229505,
        1.221383,
        1.216906,
        1.233645,
        1.230766,
        1.225874,
        1.217167,
        1.232283,
        1.273846,
        1.287853,
        1.307689,
        1.310885,
        1.291999,
        1.296148,
        1.293383,
        1.288565,
        1.281311,
        1.282316,
        1.287399,
        1.297307,
        1.28196,
        1.262546,
        1.261726,
        1.291736,
        1.303383,
        1.311772,
        1.310022,
        1.312451,
        1.302677,
        1.301726,
        1.3132,
        1.332673,
        1.346036,
        1.335401,
        1.315013,
        1.264859,
        1.270417,
        1.295389,
        1.340508,
        1.363738,
        1.369783,
        1.338028,
        1.328931,
        1.358447,
        1.360952,
        1.375901,
        1.354615,
        1.32637,
        1.324271,
        1.359909,
        1.370927,
        1.368159,
        1.349135,
        1.339005,
        1.36092,
        1.367515,
        1.357832,
        1.379714,
        1.379621,
        1.3645,
        1.361547,
        1.344497,
        1.331982,
        1.32171,
        1.368645,
        1.381434,
        1.374916,
        1.391967,
        1.400977,
        1.391182,
        1.396865,
        1.408429,
        1.397005,
        1.385149,
        1.391798,
        1.388302,
        1.394192,
        1.395925,
        1.386446,
        1.381118,
        1.373082,
        1.361593,
        1.365234,
        1.367947,
        1.364164,
        1.352779,
        1.339375,
        1.31077,
        1.305732,
        1.343826,
        1.377327,
        1.38432,
        1.380355,
        1.37179,
        1.352916,
        1.333267,
        1.308385,
        1.312472,
        1.353081,
        1.365134,
        1.370081,
        1.37337,
        1.370343,
        1.358001,
        1.364389,
        1.365498,
        1.343412,
        1.3325,
        1.344517,
        1.350099,
        1.36949,
        1.383674,
        1.382243,
        1.346656,
        1.320884,
        1.360394,
        1.379112,
        1.388588,
        1.394777,
        1.409375,
        1.399466,
        1.379645,
        1.37406,
        1.379864,
        1.383562,
        1.401649,
        1.408528,
        1.427462,
        1.421533,
        1.414935,
        1.381015,
        1.345804,
        1.368575,
        1.38038,
        1.372617,
        1.374288,
        1.389713,
        1.388253,
        1.368292,
        1.356684,
        1.34629,
        1.343999,
        1.347934,
        1.313131,
        1.3108,
        1.309817,
        1.284832,
        1.268841,
        1.281641,
        1.297403,
        1.304487,
        1.295825,
        1.270673,
        1.263175,
        1.288625,
        1.304757,
        1.29804,
        1.314845,
        1.334128,
        1.341744,
        1.338167,
        1.336148,
        1.340255,
        1.312096,
        1.306098,
        1.322221,
        1.334279,
        1.3504,
        1.344954,
        1.302834,
        1.30739,
        1.36576,
        1.359367,
        1.324492,
        1.318119,
        1.340308,
        1.337687,
        1.317684,
        1.291169,
        1.29511,
        1.30371,
        1.303565,
        1.276734,
        1.24874,
        1.267116,
        1.275635,
        1.270952,
        1.257119,
        1.270533,
        1.305189,
        1.294759,
        1.298668,
        1.296846,
        1.287092,
        1.292877,
        1.308114,
        1.281192,
        1.290404,
        1.310556,
        1.305105,
        1.284277,
        1.262752,
        1.276298,
        1.252988,
        1.263858,
        1.27922,
        1.298001,
        1.313414,
        1.321972,
        1.328465,
        1.333803,
        1.329384,
        1.328805,
        1.337554,
        1.333058,
        1.299736,
        1.337134,
        1.345974,
        1.33315,
        1.31434,
        1.326153,
        1.308471,
        1.293208,
        1.286838,
        1.277682,
        1.252363,
        1.242214,
        1.276332,
        1.27521,
        1.255242,
        1.24771,
        1.260624,
        1.265051,
        1.259489,
        1.257029,
        1.271947,
        1.271853,
        1.259417,
        1.2938,
        1.286388,
        1.246762,
        1.208612,
        1.251286,
        1.295838,
        1.29767,
        1.315715,
        1.302544,
        1.28618,
        1.27681,
        1.250003,
        1.280635,
        1.244695,
        1.266958,
        1.294407,
        1.301036,
        1.310224,
        1.310146,
        1.292398,
        1.293746,
        1.335026,
        1.332101,
        1.330289,
        1.312408,
        1.179531,
        1.156187,
        1.261,
        1.286896,
        1.255459,
        1.279243,
        1.279631,
        1.24133,
        1.130975,
        0.944409,
        0.948493,
        1.139644,
        1.256706,
        1.302838,
        1.314643,
        1.307056,
        1.298837,
        1.293474,
        1.30052,
        1.315526,
        1.320613,
        1.324733,
        1.320685,
        1.297935,
        1.298005,
        1.29976,
        1.317149,
        1.332199,
        1.339424,
        1.345849,
        1.321196,
        1.274563,
        1.192014,
        1.013886,
        1.027045,
        1.172738,
        1.224195,
        1.253179,
        1.257299,
        1.260679,
        1.290702,
        1.289759,
        1.310692,
        1.32085,
        1.334779,
        1.348311,
        1.342642,
        1.327294,
        1.320784,
        1.323712,
        1.329274,
        1.32457,
        1.313709,
        1.301211,
        1.285196,
        1.272545,
        1.291953,
        1.313518,
        1.320434,
        1.308097,
        1.304346,
        1.28209,
        1.239766,
        1.284554,
        1.324217,
        1.309108,
        1.307936,
        1.332334,
        1.320415,
        1.320071,
        1.34326,
        1.354915,
        1.351256,
        1.320605,
        1.297882,
        1.307796,
        1.298558,
        1.298964,
        1.320978,
        1.327389,
        1.329442,
        1.336533,
        1.342417,
        1.340254,
        1.322697,
        1.306541,
        1.304775,
        1.300419,
        1.296111,
        1.298709,
        1.285663,
        1.291883,
        1.313187,
        1.321036,
        1.316994,
        1.305577,
        1.296247,
        1.294668,
        1.29916,
        1.293802,
        1.319871,
        1.309069,
        1.304174,
        1.27814,
        1.249068,
        1.250985,
        1.252994,
        1.282272,
        1.308629,
        1.313738,
        1.318501,
        1.31569,
        1.32135,
        1.324068,
        1.322145,
        1.311779,
        1.297703,
        1.272637,
        1.24795,
        1.222584,
        1.244548,
        1.252304,
        1.248129,
        1.245045,
        1.236989,
        1.23465,
        1.255952,
        1.259711,
        1.246892,
        1.23029,
        1.212277,
        1.210328,
        1.210097,
        1.218612,
        1.211627,
        1.184898,
        1.175191,
        1.195835,
        1.209222,
        1.209837,
        1.197923,
        1.192192,
        1.184269,
        1.175519,
        1.184631,
        1.207733,
        1.221114,
        1.207003,
        1.182269,
        1.15644,
        1.139704,
        1.137891,
        1.149246,
        1.164881,
        1.197625,
        1.221628,
        1.226452,
        1.227772,
        1.236427,
        1.237906,
        1.247046,
        1.250588,
        1.255088,
        1.234083,
        1.207887,
        1.186525,
        1.170609,
        1.178266,
        1.163227,
        1.151172,
        1.135756,
        1.179322,
        1.149634,
        1.153574,
        1.174042,
        1.17445,
        1.201054,
        1.21682,
        1.251364,
        1.279219,
        1.294416,
        1.281028,
        1.254549,
        1.219857,
        1.1913,
        1.1814,
        1.156763,
        1.125604,
        1.135875,
        1.097496,
        1.113495,
        1.141086,
        1.134341,
        1.143847,
        1.180172,
        1.190266,
        1.192784,
        1.169288,
        1.192268,
        1.198207,
        1.162655,
        1.126641,
        1.141939,
        1.169456,
        1.156033,
        1.140763,
        1.159408,
        1.174825,
        1.176069,
        1.158757,
        1.134068,
        1.143139,
        1.136732,
        1.143815,
        1.135772,
        1.13717,
        1.141674,
        1.131468,
        1.133748,
        1.135044,
        1.143592,
        1.138764,
        1.139727,
        1.148905,
        1.148135,
        1.147418,
        1.138267,
        1.143026,
        1.131556,
        1.116686,
        1.123409,
        1.122291,
        1.133596,
        1.13229,
        1.132611,
        1.141366,
        1.13594,
        1.140116,
        1.157234,
        1.145782,
        1.149947,
        1.144426,
        1.131429,
        1.137583,
        1.144511,
        1.132976,
        1.137502,
        1.133935,
        1.130205,
        1.124523,
        1.119535,
        1.128931,
        1.135926,
        1.140705,
        1.135438,
        1.133489,
        1.13255,
        1.135843,
        1.117914,
        1.110499,
        1.134444,
        1.143348,
        1.152016,
        1.158123,
        1.162169,
        1.174859,
        1.166707,
        1.164718,
        1.162986,
        1.174004,
        1.175229,
        1.17914,
        1.180594,
        1.173218,
        1.165015,
        1.178623,
        1.17395,
        1.179328,
        1.170927,
        1.178815,
        1.176002,
        1.164472,
        1.17004,
        1.169286,
        1.158118,
        1.162864,
        1.153048,
        1.150935,
        1.16257,
        1.179626,
        1.167836,
        1.168816,
        1.175949,
        1.182016,
        1.176936,
        1.17261,
        1.174525,
        1.182546,
        1.168793,
        1.173457,
        1.180799,
        1.179507,
        1.186988,
        1.179353,
        1.192051,
        1.2048,
        1.193702,
        1.19981,
        1.180598,
        1.179626,
        1.171206,
        1.160602,
        1.171976,
        1.147624,
        1.172049,
        1.162868,
        1.176651,
        1.170248,
        1.177879,
        1.180234,
        1.167109,
        1.178206,
        1.179596,
        1.180977,
        1.168204,
        1.170735,
        1.169407,
        1.182859,
        1.181765,
        1.17697,
        1.171467,
        1.168833,
        1.152049,
        1.162816,
        1.159819,
        1.158617,
        1.161907,
        1.174892,
        1.166735,
        1.159028,
        1.177744,
        1.144322,
        1.145331,
        1.146761,
        1.148346,
        1.149822,
        1.150904,
        1.151218,
        1.150372,
        1.147972,
        1.143925,
        1.139347,
        1.135654,
        1.134261,
        1.136083,
        1.140019,
        1.144467,
        1.147823,
        1.148869,
        1.147916,
        1.14566,
        1.142796,
        1.143389,
        1.141551,
        1.139426,
        1.136849,
        1.133816,
        1.130974,
        1.129133,
        1.129102,
        1.131355,
        1.135022,
        1.138898,
        1.141777,
        1.14279,
        1.142413,
        1.141459,
        1.140739,
        1.140868,
        1.141661,
        1.142734,
        1.143705,
        1.144269,
        1.144433,
        1.144286,
        1.143914,
        1.143377,
        1.14263,
        1.1416,
        1.140213,
        1.138442,
        1.136429,
        1.134361,
        1.132422,
        1.130806,
        1.129732,
        1.129425,
        1.130111,
        1.131849,
        1.134034,
        1.135895,
        1.136661
      ],
      "range":1
    }
  }
]
